scienlib
