Metadata-Version: 2.1
Name: scienlib
Version: 1.1
Summary: scienlib is a scientific python library that adds math functions and adds other functions such as physics
Home-page: https://github.com/dylan14567/scienlib
Author: dylan14567
Author-email: 
License: UNKNOWN
Project-URL: Bug Tracker, https://github.com/dylan14567/scienlib/issues
Project-URL: Documentation, https://dylan14567.github.io/2021/04/28/scienlib-documentation.html
Keywords: scienlib
Platform: UNKNOWN
Classifier: Programming Language :: Python :: 3
Classifier: License :: OSI Approved :: MIT License
Classifier: Operating System :: OS Independent
Requires-Python: >=3.6
